smb_storage.py
smb_storage-0.1.0.dist-info/WHEEL
smb_storage-0.1.0.dist-info/METADATA
smb_storage-0.1.0.dist-info/RECORD
